README.txt
setup.cfg
setup.py
src/QTLibrary/__init__.py
src/QTLibrary/version.py
src/QTLibrary/keywords/__init__.py
src/QTLibrary/keywords/_element.py
src/QTLibrary/keywords/_logging.py
src/QTLibrary/keywords/_runonfailure.py
src/QTLibrary/keywords/keywordgroup.py
src/robotframework_qtlibrary.egg-info/PKG-INFO
src/robotframework_qtlibrary.egg-info/SOURCES.txt
src/robotframework_qtlibrary.egg-info/dependency_links.txt
src/robotframework_qtlibrary.egg-info/requires.txt
src/robotframework_qtlibrary.egg-info/top_level.txt